sec_company_facts/__init__.py
sec_company_facts/core.py
sec_company_facts/py.typed
sec_company_facts-0.1.4.dist-info/licenses/LICENSE.md
sec_company_facts-0.1.4.dist-info/METADATA
sec_company_facts-0.1.4.dist-info/WHEEL
sec_company_facts-0.1.4.dist-info/top_level.txt
sec_company_facts-0.1.4.dist-info/RECORD
