Metadata-Version: 2.4
Name: sec_company_facts
Version: 0.1.4
Summary: Fetch SEC 10-K company facts dataframes
Author-email: Marcin Anforowicz <manforowicz@gmail.com>
License-Expression: MIT
Project-URL: Homepage, https://github.com/manforowicz/sec_company_facts
Requires-Python: >=3.11
License-File: LICENSE.md
Requires-Dist: pandas
Requires-Dist: requests
Provides-Extra: test
Requires-Dist: pytest; extra == "test"
Requires-Dist: pytest-cov; extra == "test"
Dynamic: license-file
